emp_orderly_types/__init__.py
emp_orderly_types/assets.py
emp_orderly_types/interval.py
emp_orderly_types/market.py
emp_orderly_types/orders.py
emp_orderly_types/position.py
emp_orderly_types/register.py
emp_orderly_types/status.py
emp_orderly_types-1.0.dist-info/METADATA
emp_orderly_types-1.0.dist-info/WHEEL
emp_orderly_types-1.0.dist-info/top_level.txt
emp_orderly_types-1.0.dist-info/RECORD
