Metadata-Version: 2.1
Name: emp-orderly-types
Version: 1.0
Classifier: Programming Language :: Python :: 3
Classifier: Programming Language :: Python :: 3.10
Classifier: Programming Language :: Python :: 3.11
Classifier: Programming Language :: Python :: 3.12
Requires-Python: >=3.10, <3.13
Requires-Dist: base58 ==2.1.1
Requires-Dist: cryptography ==42.0.5
Requires-Dist: eth-typing ==4.1.0
Requires-Dist: eth-utils ==4.1.0
Requires-Dist: httpx ==0.27.0
Requires-Dist: pandas ==2.2.2
Requires-Dist: pydantic >=2.7.0
Requires-Dist: python-dotenv ==1.0.1
Requires-Dist: requests ==2.31.0
